CAD_Recognition/__init__.py
CAD_Recognition/data_load.py
CAD_Recognition/devide_no_test.py
CAD_Recognition/features.py
CAD_Recognition/programs.py
CAD_Recognition-0.0.9.dist-info/METADATA
CAD_Recognition-0.0.9.dist-info/WHEEL
CAD_Recognition-0.0.9.dist-info/top_level.txt
CAD_Recognition-0.0.9.dist-info/RECORD
