Metadata-Version: 2.1
Name: CAD-Recognition
Version: 0.0.9
Summary: Image kernel.
Home-page: https://github.com/kenblikylee/imgkernel
Author: francis
Author-email: kenbliky@gmail.com
License: UNKNOWN
Platform: UNKNOWN
Classifier: Programming Language :: Python :: 3
Classifier: Operating System :: OS Independent
Requires-Python: >=3.5
